rse_api_client/__init__.py
rse_api_client/rse_api_client.py
rse_api_client-0.1.2.dist-info/LICENSE
rse_api_client-0.1.2.dist-info/METADATA
rse_api_client-0.1.2.dist-info/WHEEL
rse_api_client-0.1.2.dist-info/entry_points.txt
rse_api_client-0.1.2.dist-info/top_level.txt
rse_api_client-0.1.2.dist-info/RECORD
