Metadata-Version: 2.2
Name: rse_api_client
Version: 0.1.2
Summary: A client for RSE API
Home-page: https://github.com/danicode/rse-api-client
Author: Daniel Anzawa
Author-email: danielanzawa@gmail.com
Classifier: Programming Language :: Python :: 3
Classifier: License :: OSI Approved :: MIT License
Classifier: Operating System :: OS Independent
License-File: LICENSE
Requires-Dist: setuptools
Requires-Dist: requests
Requires-Dist: python-dotenv
Dynamic: author
Dynamic: author-email
Dynamic: classifier
Dynamic: description
Dynamic: description-content-type
Dynamic: home-page
Dynamic: requires-dist
Dynamic: summary
